assign_uprn/__init__.py
assign_uprn/_modidx.py
assign_uprn/api_calls.py
assign_uprn-0.2.1.dist-info/licenses/LICENSE
assign_uprn-0.2.1.dist-info/METADATA
assign_uprn-0.2.1.dist-info/WHEEL
assign_uprn-0.2.1.dist-info/entry_points.txt
assign_uprn-0.2.1.dist-info/top_level.txt
assign_uprn-0.2.1.dist-info/RECORD
