Metadata-Version: 2.4
Name: assign-uprn
Version: 0.2.1
Summary: python client for ASSIGN api functions
Home-page: https://git.sr.ht/~joeldn/assign-uprn
Author: joeldn
Author-email: joeldn@tuta.io
Requires-Python: >=3.10
License-File: LICENSE
Requires-Dist: dotenv>=0.9.9
Requires-Dist: requests>=2.32.5
Requires-Dist: urllib3>=2.5.0
Dynamic: author
Dynamic: author-email
Dynamic: home-page
Dynamic: license-file
Dynamic: requires-python
